README.md
setup.cfg
setup.py
snowflake/connector/__init__.py
snowflake/connector/arrow_context.py
snowflake/connector/auth.py
snowflake/connector/auth_by_plugin.py
snowflake/connector/auth_default.py
snowflake/connector/backport_makefile.py
snowflake/connector/chunk_downloader.py
snowflake/connector/compat.py
snowflake/connector/connection.py
snowflake/connector/constants.py
snowflake/connector/converter.py
snowflake/connector/converter_snowsql.py
snowflake/connector/cursor.py
snowflake/connector/dbapi.py
snowflake/connector/description.py
snowflake/connector/encryption_util.py
snowflake/connector/errorcode.py
snowflake/connector/errors.py
snowflake/connector/file_compression_type.py
snowflake/connector/file_transfer_agent.py
snowflake/connector/file_util.py
snowflake/connector/gzip_decoder.py
snowflake/connector/incident.py
snowflake/connector/json_result.py
snowflake/connector/local_util.py
snowflake/connector/mixin.py
snowflake/connector/network.py
snowflake/connector/ocsp_asn1crypto.py
snowflake/connector/ocsp_snowflake.py
snowflake/connector/proxy.py
snowflake/connector/remote_storage_util.py
snowflake/connector/secret_detector.py
snowflake/connector/sfbinaryformat.py
snowflake/connector/sfdatetime.py
snowflake/connector/sqlstate.py
snowflake/connector/ssd_internal_keys.py
snowflake/connector/ssl_wrap_socket.py
snowflake/connector/ssl_wrap_util.py
snowflake/connector/telemetry.py
snowflake/connector/telemetry_oob.py
snowflake/connector/time_util.py
snowflake/connector/util_text.py
snowflake/connector/version.py
snowflake/connector/tool/__init__.py
snowflake/connector/tool/dump_certs.py
snowflake/connector/tool/dump_ocsp_response.py
snowflake/connector/tool/dump_ocsp_response_cache.py
snowflake/connector/tool/probe_connection.py
snowflake_connector_python_lite.egg-info/PKG-INFO
snowflake_connector_python_lite.egg-info/SOURCES.txt
snowflake_connector_python_lite.egg-info/dependency_links.txt
snowflake_connector_python_lite.egg-info/namespace_packages.txt
snowflake_connector_python_lite.egg-info/requires.txt
snowflake_connector_python_lite.egg-info/top_level.txt